{"Kv4Xi4oLLfOY73Q9XdCLbg==":"lgoog1kopie-936x937.png","eoYU/aiNC4Ce+rsKshUaWw==":"jumbotron2.jpg","O++2rzx+kWXb6A1k8GH21g==":"begin-2000x1412.png","jsrya749Pe6lURO17z18NQ==":"begin-1-2000x1412.png","dBQY3SbYAKd2d+NRlVrb0w==":"begin-2-2000x1412.png","VxnemkSkbxCvh8joB31+zA==":"begin-3-2000x1412.png","irQMxagWcgbf8WFoMyj5bA==":"begin-4-2000x1412.png","Jzf2bu3IDl61DB7wMiLGtA==":"begin-5-2000x1412.png","6QSuFHlDLAg/Hhn/jQ6I/g==":"begin-6-2000x1412.png","ZUDft6pDi3Am8wF/DM9WGQ==":"vb2-2000x1412.png","KzdZlxBeTgIn0sXzm+6NWQ==":"vb2-1-2000x1412.png","dPR+n1j63ICPKwSRvCtsUQ==":"vb2-2-2000x1412.png","RenQFmWWdoTtl/oHpef9qg==":"vb2-3-2000x1412.png","MMAPPQ5Cpnad7nEOuFeL6Q==":"vb2-4-2000x1412.png","Al8yBayYVoAh2lhqnw/D9Q==":"vb2-5-2000x1412.png","VAsDAOYHsxyYStKYb/b/Jg==":"vb2-6-2000x1412.png","6JaPuh/sEFd0mCAOjo1fwg==":"vb2-7-2000x1412.png","XsDGEv2qsFUlSErpk0CHQQ==":"vb2-8-2000x1412.png","ihlkf69UyfSmhSyJ1Jvc6w==":"jumbotron.jpg","yXRHCRe16MzXJbHZkzDKAg==":"voorbladsite-2000x1414.png","xK0Kz6rfAWU39CrcZ7bPXg==":"voorbladsite-1-2000x1414.png","aKq6AcJRKIGWT+MxvpXjhQ==":"voorbladsite2-2000x1414.png","Pj7GqgHxXx5sbnEQDNo3xQ==":"voorbladsite2-1-2000x1414.png","WbMRXciw7YJeoXdEv3BDgw==":"voorbladsite2-2-2000x1414.png","94OeolP8aK4bAf8NEoGkFA==":"mbr-892x593.jpg","7r4xL3ufPdj+gK92PWk7bA==":"mbr-508x286.jpg","qxlw4ZxzagB+tijA4JkcRQ==":"mini-2000x1426.png","2eZiCiyIcwlZQ8adHSb5Cg==":"mini-1-2000x1426.png","dHbQbLYiL6kIEuloahj1Xg==":"mini-2-2000x1426.png","7M8lV19iWMYt8UEe/UQ7dQ==":"mini-3-2000x1426.png","wPA7iIwbb+ClyaCsgPRVDQ==":"mini-4-2000x1426.png","5QQAapOntnoodNoJS45BUA==":"mbr-1920x1080.jpg","2f3qplVqM65yikxVzJFisA==":"mbr-1920x1280.jpg","8UbI4cKZAkFL+0arCL/Wjg==":"mbr-1920x1208.jpg","7HyorOoDZDu0IGzscZzKRQ==":"img-4449-352x264.jpg","VOgm9VZdQOiscuf+B9EgCA==":"stalker3-352x198.jpg","lGpy3mxStcFZZfPcEd4V7Q==":"mini-5-2000x1426.png","pbryBwcKgLQn7AuXbEagGw==":"mini-6-2000x1426.png","7bjkHYKxgBTOYvxQAWbOTw==":"20-stalker-sublime-escultura-temporal-de-tarkovsky--1200x763.jpg","AGEksS0bzUdiCsTgX3pfsA==":"98d875959b75b90eebb87958ff03e0e2-563x375.jpg","G6nAU15Uqq//tn0YSb5PCg==":"98d875959b75b90eebb87958ff03e0e2-1-563x375.jpg","ZQ9NAxHvrkvYkbWd+djHUQ==":"10710407_913528132009001_616672280147562642_o-904x602.jpg","QeyvmhvqLrxP+3ldxSKD/w==":"20-stalker-sublime-escultura-temporal-de-tarkovsky--1-1200x763.jpg","oXqulmLhzU3oGvHCGcefow==":"20-stalker-sublime-escultura-temporal-de-tarkovsky--2-1200x763.jpg","wFD+NQgaDK3x5Revxhh6vw==":"tumblr_mexhbgpvjg1raxjpco1-1280-1000x1500.jpg","/vAYLj+GxdXIs/B0aQxd+Q==":"tumblr_mexhbgpvjg1raxjpco1-1281-1000x1500.jpg","YUFxIB4NdCuW/W4gIv3W1w==":"tumblr_mexhbgpvjg1raxjpco1-1282-1000x1500.jpg","Mq/dsyxzadmCcBibBDF3mQ==":"20-stalker-sublime-escultura-temporal-de-tarkovsky--1259x800.jpg","Rs94uQExnzGUI2WiUfsh0g==":"10710407_913528132009001_616672280147562642_o-1500x999.jpg","lRJck3IY5CoXYCEj5ok/JA==":"tumblr_mexhbgpvjg1raxjpco1-1283-1000x1500.jpg","LIpaGIb8hmskfzIUJ1Q1aw==":"20-stalker-sublime-escultura-temporal-de-tarkovsky--676x430.jpg","psSvNNnOGbOkRS+44F35Og==":"10710407_913528132009001_616672280147562642_o-676x450.jpg","O+d75S5PBAHdHPe8UU8JNQ==":"tumblr_mexhbgpvjg1raxjpco1-1280-676x1014.jpg","hgGxryolAeeef4Tz4rYcug==":"ahhhh-1366x768.jpg","RB6eFCLbBeHChlGdULzuBQ==":"ahhhh-1-1366x768.jpg","Q8kyWdiPLYJ/4F1Ss+9IyA==":"03.jpg","/y7keZ9fEdjlURJFTcT+LA==":"mini-2548x1817.png","pH/nem+dW5M40kfOpIBI/A==":"mini-1-2548x1817.png","Lnlyo8Y2+XH3rf3rTEBBdQ==":"mini-2-2548x1817.png","RxyjYVFO/GDmUrxnlCI1FQ==":"mini-2706x1930.png","O1llsb50fCxjbMEBIZNXpQ==":"mini-1-2706x1930.png","k0yLwb9kX8997sBOnIuCJA==":"ahhhh-2-1366x768.jpg","WoGHDpOr01U4v7hdtYBEqQ==":"ahhhh-3-1366x768.jpg","TpAM4K1L6Cd2y6tijPbpvQ==":"img-4303-2000x1333.jpg","5T417c5GgM/JLDQ1/kgZ1g==":"img-4311-2000x1333.jpg","e52+Rc/9oEAuLlcwj87UBA==":"img-4390-2000x1333.jpg","F9cTwoqUgUfNK5ZAajLYZw==":"img-4393-2000x1333.jpg","aBo/pG1Bl5MdMkqG7du5pw==":"img-4394-2000x1333.jpg","kazHH/iEXCQN6IPRDw6GyA==":"img-4320-2000x1333.jpg","1v76zAVih+LRoAvLUT45Hg==":"img-4319-2000x1333.jpg","QgkszyPE5SNdisJ3Us8ivQ==":"img-9137-2000x1333.jpg","JqpSjpOv45LbwE6awQT/bg==":"jjjj-2704x1934.jpg","B9HXE3KHjOGk/x70xt/opg==":"jjjj-1-2704x1934.jpg","pJXFMxElO7NTHZysUN8PFQ==":"jjjj-1014x725.jpg","YDg/dfCgGymcGHngjUBBKw==":"jjjj-1-1014x725.jpg","T8b7fL1FTzTHS8TWpjGQPw==":"jjjj-1776x1270.jpg","AQnWpatTnPidBLUYhP99sA==":"jjjj-2000x1431.jpg","t7uF+05vljIeLAPlvs43Vg==":"jjjj-2-1014x725.jpg","Xd0q2l69BUmshvEDJrljeQ==":"jjjj-3-1014x725.jpg","fU+oLTskPgJTDz9KK4aSEQ==":"jjjj-4-1014x725.jpg","o1Ix/h7ajqHXC+9FEwGASQ==":"foto%201-1488x1068.jpg","uXVq+I25eMeyzjK2v6b7JA==":"49834070_135886870671144_4282589273267372032_n-1488x1116.png","RSSucRvLHshhp+TbGFimJA==":"50007541_288053332057079_7624324359292715008_n-1488x1116.jpg","bOFBUEr/XKIcXlVfJ5ciog==":"49834070_135886870671144_4282589273267372032_n-1488x1116.jpg","NSY9hPDTbcc2q7g8AevgJQ==":"aa-1488x1116.jpg","/IfYvVmX1bWO71z4BtW3mQ==":"aa-1-1488x1116.jpg","wtvYY3G1PJZGKNV4ettj1w==":"foto%201-1488x1068.jpg","LknA4WusD1TF9aHBPKzpPA==":"49638331_336396866948545_1723349593090949120_n-1488x1116.jpg","ok5oqN16I0M1c7YjCQmUcw==":"aad-1488x1116.jpg","umY5lijelQsPv68JKMhVAQ==":"zzzzzz-1488x1116.jpg","5xo1IiWUJ2UxEM23Ipo3cg==":"zee-1488x1116.jpg","v1sH8MZSvTCo5qAPqF3O2Q==":"er-1488x1116.jpg","lEddSixi+Txpj46Nr03ELQ==":"er-1-1488x1116.jpg","Z0eH60zf397J+lC6iSZb0Q==":"bla-1488x1116.jpg","beQIC0q+OGzCP4PnRJXrYQ==":"zaza-1488x1116.jpg"}